pipbert-9.1.8.dist-info/licenses/LICENSE
pybert/__init__.py
pybert/__main__.py
pybert/cli.py
pybert/common.py
pybert/configuration.py
pybert/py.typed
pybert/pybert.py
pybert/results.py
pybert/gui/__init__.py
pybert/gui/handler.py
pybert/gui/help.py
pybert/gui/plot.py
pybert/gui/view.py
pybert/gui/images/icon.png
pybert/models/__init__.py
pybert/models/bert.py
pybert/models/cdr.py
pybert/models/dfe.py
pybert/models/fec.py
pybert/models/tx_tap.py
pybert/models/viterbi.py
pybert/parsers/__init__.py
pybert/parsers/hspice.py
pybert/solvers/__init__.py
pybert/solvers/solver.py
pybert/solvers/simbeor/__init__.py
pybert/threads/__init__.py
pybert/threads/optimization.py
pybert/threads/sim.py
pybert/threads/stoppable.py
pybert/utility/__init__.py
pybert/utility/channel.py
pybert/utility/functional.py
pybert/utility/ibisami.py
pybert/utility/jitter.py
pybert/utility/math.py
pybert/utility/python.py
pybert/utility/sigproc.py
pybert/utility/sparam.py
pipbert-9.1.8.dist-info/METADATA
pipbert-9.1.8.dist-info/WHEEL
pipbert-9.1.8.dist-info/entry_points.txt
pipbert-9.1.8.dist-info/top_level.txt
pipbert-9.1.8.dist-info/RECORD
