Metadata-Version: 2.4
Name: pipbert
Version: 9.1.8
Summary: Serial communication link bit error rate tester simulator, written in Python.
Author-email: David Banas <capn.freako@gmail.com>
Project-URL: Wiki, https://github.com/capn-freako/PyBERT/wiki
Project-URL: Installation, https://github.com/capn-freako/PyBERT/wiki/instant_gratification
Project-URL: FAQ, https://github.com/capn-freako/PyBERT/wiki/pybert_faq
Project-URL: GitHub, https://github.com/capn-freako/PyBERT
Project-URL: PyPi, https://pypi.org/project/PipBERT/
Keywords: bert,communication,simulator
Classifier: Development Status :: 5 - Production/Stable
Classifier: Environment :: Console
Classifier: Intended Audience :: Developers
Classifier: Intended Audience :: Education
Classifier: Intended Audience :: Telecommunications Industry
Classifier: Intended Audience :: Science/Research
Classifier: Operating System :: OS Independent
Classifier: Programming Language :: Python
Classifier: Programming Language :: Python :: 3.10
Classifier: Programming Language :: Python :: 3.11
Classifier: Programming Language :: Python :: 3.12
Classifier: Programming Language :: Python :: Implementation :: CPython
Classifier: Topic :: Adaptive Technologies
Classifier: Topic :: Scientific/Engineering
Classifier: Topic :: Scientific/Engineering :: Electronic Design Automation (EDA)
Classifier: Topic :: Scientific/Engineering :: Visualization
Classifier: Topic :: System :: Emulators
Classifier: Topic :: System :: Networking
Classifier: Topic :: Utilities
Requires-Python: <3.13,>=3.10
License-File: LICENSE
Requires-Dist: enable>=6.1.0
Requires-Dist: kiwisolver
Requires-Dist: pychopmarg>=3.1.2
Requires-Dist: pyibis-ami>=7.3.1
Requires-Dist: pyside6<6.7
Requires-Dist: pyyaml>=6
Requires-Dist: scikit-rf>=0.29
Requires-Dist: typing_extensions
Dynamic: license-file
